[
{"page_id":418944,"title":"Glenn Beck","score":536837.015918057},
{"page_id":9294053,"title":"The Story of Miss Moppet","score":519834.667804115},
{"page_id":88493,"title":"Howard Zinn","score":463460.0957325797},
{"page_id":534366,"title":"Barack Obama","score":410083.1142749298},
{"page_id":8877168,"title":"WikiLeaks","score":396022.54475095385},
{"page_id":2957039,"title":"Sex offender","score":386360.6041067157},
{"page_id":56472,"title":"Benjamin Netanyahu","score":381264.330519586},
{"page_id":699349,"title":"Ben Roethlisberger","score":379533.1572378222},
{"page_id":216169,"title":"Tom DeLay","score":364560.4227018566},
{"page_id":25433,"title":"Ronald Reagan","score":361189.0521880948},
{"page_id":21566,"title":"Noam Chomsky","score":350439.16680067056},
{"page_id":7515849,"title":"Syria","score":320691.6862478457},
{"page_id":18247304,"title":"Edward Said","score":317795.0436176242},
{"page_id":2008784,"title":"Gilad Atzmon","score":304828.0545955964},
{"page_id":92656,"title":"Same-sex marriage","score":301763.8106604607},
{"page_id":19344654,"title":"BBC","score":291574.46615689486},
{"page_id":5043505,"title":"Jack Thompson (activist)","score":282247.2868713735},
{"page_id":741886,"title":"Meg Whitman","score":278894.8844727703},
{"page_id":240940,"title":"LeBron James","score":267099.25652441144},
{"page_id":39942,"title":"Jennifer Aniston","score":266528.8267463719},
{}]
