[
{"page_id":33121168,"title":"Occupy Wall Street","score":1255449.2381698205},
{"page_id":20082093,"title":"Presidency of Barack Obama","score":880452.8361573197},
{"page_id":534366,"title":"Barack Obama","score":834610.8470550677},
{"page_id":106128,"title":"First Crusade","score":722736.0665868473},
{"page_id":35134492,"title":"Toulouse and Montauban shootings","score":688940.9868981505},
{"page_id":183628,"title":"FIS Alpine Ski World Cup","score":571854.0041109261},
{"page_id":28840,"title":"Sharia","score":557737.4705736305},
{"page_id":26750,"title":"Sri Lanka","score":514689.2338374713},
{"page_id":12319832,"title":"Transformers: Revenge of the Fallen","score":506014.7349591144},
{"page_id":30345,"title":"Talmud","score":484535.09994225844},
{"page_id":28246,"title":"Sufism","score":444252.52299378166},
{"page_id":167020,"title":"Islamic art","score":441873.5538594008},
{"page_id":4724183,"title":"Women in Islam","score":431650.0758849989},
{"page_id":18600829,"title":"Jeff Gordon","score":423306.07624210365},
{"page_id":25405,"title":"Rugby union","score":422008.0387460758},
{"page_id":360759,"title":"One Piece","score":400198.19003963895},
{"page_id":1040159,"title":"Who is a Jew?","score":389554.0154521887},
{"page_id":426208,"title":"Mitt Romney","score":388482.55288113526},
{"page_id":14810,"title":"Islamic calendar","score":377910.9135055483},
{"page_id":1415882,"title":"Helena Guergis","score":375356.0033013112},
{}]
